Workbook

Sheet Setup
A1: Portfolio Simulator — Test Spreadsheet
A3: Monthly Investment | B3: 1000
A4: Investment Years | B4: 3
A5: Tax Rate | B5: 0.3
A6: Total Months | B6: 37
A8: Ticker | B8: Name | C8: Allocation %
A9: XLK | B9: Information Technology | C9: 0.6
A10: XLV | B10: Health Care | C10: 0.4
A13: Month | B13: MM Rate | C13: XLK High | D13: XLK Close | E13: XLK Div/Share | F13: XLV High | G13: XLV Close | H13: XLV Div/Share
A14: Feb 2023 | B14: 0.0457 | C14: 72.294998 | D14: 68.260002 | E14: 0 | F14: 134.81 | G14: 127.17 | H14: 0
A15: Mar 2023 | B15: 0.0465 | C15: 75.574997 | D15: 75.504997 | E15: 0.158 | F15: 129.7 | G15: 129.46001 | H15: 0.489
A16: Apr 2023 | B16: 0.0483 | C16: 75.754997 | D16: 75.415001 | E16: 0 | F16: 135.81 | G16: 133.53 | H16: 0
A17: May 2023 | B17: 0.0506 | C17: 84.019997 | D17: 82.139999 | E17: 0 | F17: 134.89999 | G17: 127.83 | H17: 0
A18: Jun 2023 | B18: 0.0508 | C18: 88.150002 | D18: 86.93 | E18: 0.181 | F18: 133.25 | G18: 132.73 | H18: 0.542
A19: Jul 2023 | B19: 0.0512 | C19: 90.730003 | D19: 89.175003 | E19: 0 | F19: 136.85001 | G19: 134.14999 | H19: 0
A20: Aug 2023 | B20: 0.0533 | C20: 89.514999 | D20: 87.830002 | E20: 0 | F20: 136.53 | G20: 133.21001 | H20: 0
A21: Sep 2023 | B21: 0.0533 | C21: 88.690002 | D21: 81.964996 | E21: 0.18 | F21: 134.24001 | G21: 128.74001 | H21: 0.54
A22: Oct 2023 | B22: 0.0533 | C22: 86.415001 | D22: 82.004997 | E22: 0 | F22: 131.92 | G22: 124.54 | H22: 0
A23: Nov 2023 | B23: 0.0533 | C23: 93.449997 | D23: 92.580002 | E23: 0 | F23: 131.39 | G23: 131.31 | H23: 0
A24: Dec 2023 | B24: 0.0533 | C24: 96.860001 | D24: 96.239998 | E24: 0.211 | F24: 136.7 | G24: 136.38 | H24: 0.598
A25: Jan 2024 | B25: 0.0533 | C25: 103.075 | D25: 98.839996 | E25: 0 | F25: 141.75 | G25: 140.38 | H25: 0
... A50: Feb 2026 | B50: 0 | C50: 146.14999 | D50: 141.13 | E50: 0 | F50: 157.8 | G50: 157.71001 | H50: 0

Sheet Monthly Sim
A1: Month | B1: MM Rate | C1: Prior Div Bal | D1: MM Interest | E1: Div Bal After Int | F1: XLK Invested | G1: XLK Shares | H1: XLK Cum Shares | I1: XLK Divs | J1: XLK Value | K1: XLV Invested | L1: XLV Shares | M1: XLV Cum Shares | N1: XLV Divs | O1: XLV Value | P1: Monthly Divs | Q1: Div Bal End | R1: Cum Invested | S1: Portfolio Value | T1: MM-Only Bal
A2: =Setup!A14 | B2: =Setup!B14 | C2: 0 | D2: =ROUND(C2*B2/12,2) | E2: =C2+D2 | F2: =Setup!$B$3*Setup!$C$9 | G2: =IF(Setup!C14>0,F2/Setup!C14,0) | H2: =G2 | I2: =H2*Setup!E14 | J2: =H2*Setup!D14 | K2: =Setup!$B$3*Setup!$C$10 | L2: =IF(Setup!F14>0,K2/Setup!F14,0) | M2: =L2 | N2: =M2*Setup!H14 | O2: =M2*Setup!G14 | P2: =I2+N2 | Q2: =E2+P2 | R2: =F2+K2 | S2: =J2+O2 | T2: =ROUND(0*(1+B2/12),2)+Setup!$B$3
A3: =Setup!A15 | B3: =Setup!B15 | C3: =Q2 | D3: =ROUND(C3*B3/12,2) | E3: =C3+D3 | F3: =Setup!$B$3*Setup!$C$9 | G3: =IF(Setup!C15>0,F3/Setup!C15,0) | H3: =H2+G3 | I3: =H3*Setup!E15 | J3: =H3*Setup!D15 | K3: =Setup!$B$3*Setup!$C$10 | L3: =IF(Setup!F15>0,K3/Setup!F15,0) | M3: =M2+L3 | N3: =M3*Setup!H15 | O3: =M3*Setup!G15 | P3: =I3+N3 | Q3: =E3+P3 | R3: =R2+F3+K3 | S3: =J3+O3 | T3: =ROUND(T2*(1+B3/12),2)+Setup!$B$3
A4: =Setup!A16 | B4: =Setup!B16 | C4: =Q3 | D4: =ROUND(C4*B4/12,2) | E4: =C4+D4 | F4: =Setup!$B$3*Setup!$C$9 | G4: =IF(Setup!C16>0,F4/Setup!C16,0) | H4: =H3+G4 | I4: =H4*Setup!E16 | J4: =H4*Setup!D16 | K4: =Setup!$B$3*Setup!$C$10 | L4: =IF(Setup!F16>0,K4/Setup!F16,0) | M4: =M3+L4 | N4: =M4*Setup!H16 | O4: =M4*Setup!G16 | P4: =I4+N4 | Q4: =E4+P4 | R4: =R3+F4+K4 | S4: =J4+O4 | T4: =ROUND(T3*(1+B4/12),2)+Setup!$B$3
A5: =Setup!A17 | B5: =Setup!B17 | C5: =Q4 | D5: =ROUND(C5*B5/12,2) | E5: =C5+D5 | F5: =Setup!$B$3*Setup!$C$9 | G5: =IF(Setup!C17>0,F5/Setup!C17,0) | H5: =H4+G5 | I5: =H5*Setup!E17 | J5: =H5*Setup!D17 | K5: =Setup!$B$3*Setup!$C$10 | L5: =IF(Setup!F17>0,K5/Setup!F17,0) | M5: =M4+L5 | N5: =M5*Setup!H17 | O5: =M5*Setup!G17 | P5: =I5+N5 | Q5: =E5+P5 | R5: =R4+F5+K5 | S5: =J5+O5 | T5: =ROUND(T4*(1+B5/12),2)+Setup!$B$3
A6: =Setup!A18 | B6: =Setup!B18 | C6: =Q5 | D6: =ROUND(C6*B6/12,2) | E6: =C6+D6 | F6: =Setup!$B$3*Setup!$C$9 | G6: =IF(Setup!C18>0,F6/Setup!C18,0) | H6: =H5+G6 | I6: =H6*Setup!E18 | J6: =H6*Setup!D18 | K6: =Setup!$B$3*Setup!$C$10 | L6: =IF(Setup!F18>0,K6/Setup!F18,0) | M6: =M5+L6 | N6: =M6*Setup!H18 | O6: =M6*Setup!G18 | P6: =I6+N6 | Q6: =E6+P6 | R6: =R5+F6+K6 | S6: =J6+O6 | T6: =ROUND(T5*(1+B6/12),2)+Setup!$B$3
A7: =Setup!A19 | B7: =Setup!B19 | C7: =Q6 | D7: =ROUND(C7*B7/12,2) | E7: =C7+D7 | F7: =Setup!$B$3*Setup!$C$9 | G7: =IF(Setup!C19>0,F7/Setup!C19,0) | H7: =H6+G7 | I7: =H7*Setup!E19 | J7: =H7*Setup!D19 | K7: =Setup!$B$3*Setup!$C$10 | L7: =IF(Setup!F19>0,K7/Setup!F19,0) | M7: =M6+L7 | N7: =M7*Setup!H19 | O7: =M7*Setup!G19 | P7: =I7+N7 | Q7: =E7+P7 | R7: =R6+F7+K7 | S7: =J7+O7 | T7: =ROUND(T6*(1+B7/12),2)+Setup!$B$3
A8: =Setup!A20 | B8: =Setup!B20 | C8: =Q7 | D8: =ROUND(C8*B8/12,2) | E8: =C8+D8 | F8: =Setup!$B$3*Setup!$C$9 | G8: =IF(Setup!C20>0,F8/Setup!C20,0) | H8: =H7+G8 | I8: =H8*Setup!E20 | J8: =H8*Setup!D20 | K8: =Setup!$B$3*Setup!$C$10 | L8: =IF(Setup!F20>0,K8/Setup!F20,0) | M8: =M7+L8 | N8: =M8*Setup!H20 | O8: =M8*Setup!G20 | P8: =I8+N8 | Q8: =E8+P8 | R8: =R7+F8+K8 | S8: =J8+O8 | T8: =ROUND(T7*(1+B8/12),2)+Setup!$B$3
A9: =Setup!A21 | B9: =Setup!B21 | C9: =Q8 | D9: =ROUND(C9*B9/12,2) | E9: =C9+D9 | F9: =Setup!$B$3*Setup!$C$9 | G9: =IF(Setup!C21>0,F9/Setup!C21,0) | H9: =H8+G9 | I9: =H9*Setup!E21 | J9: =H9*Setup!D21 | K9: =Setup!$B$3*Setup!$C$10 | L9: =IF(Setup!F21>0,K9/Setup!F21,0) | M9: =M8+L9 | N9: =M9*Setup!H21 | O9: =M9*Setup!G21 | P9: =I9+N9 | Q9: =E9+P9 | R9: =R8+F9+K9 | S9: =J9+O9 | T9: =ROUND(T8*(1+B9/12),2)+Setup!$B$3
A10: =Setup!A22 | B10: =Setup!B22 | C10: =Q9 | D10: =ROUND(C10*B10/12,2) | E10: =C10+D10 | F10: =Setup!$B$3*Setup!$C$9 | G10: =IF(Setup!C22>0,F10/Setup!C22,0) | H10: =H9+G10 | I10: =H10*Setup!E22 | J10: =H10*Setup!D22 | K10: =Setup!$B$3*Setup!$C$10 | L10: =IF(Setup!F22>0,K10/Setup!F22,0) | M10: =M9+L10 | N10: =M10*Setup!H22 | O10: =M10*Setup!G22 | P10: =I10+N10 | Q10: =E10+P10 | R10: =R9+F10+K10 | S10: =J10+O10 | T10: =ROUND(T9*(1+B10/12),2)+Setup!$B$3
A11: =Setup!A23 | B11: =Setup!B23 | C11: =Q10 | D11: =ROUND(C11*B11/12,2) | E11: =C11+D11 | F11: =Setup!$B$3*Setup!$C$9 | G11: =IF(Setup!C23>0,F11/Setup!C23,0) | H11: =H10+G11 | I11: =H11*Setup!E23 | J11: =H11*Setup!D23 | K11: =Setup!$B$3*Setup!$C$10 | L11: =IF(Setup!F23>0,K11/Setup!F23,0) | M11: =M10+L11 | N11: =M11*Setup!H23 | O11: =M11*Setup!G23 | P11: =I11+N11 | Q11: =E11+P11 | R11: =R10+F11+K11 | S11: =J11+O11 | T11: =ROUND(T10*(1+B11/12),2)+Setup!$B$3
A12: =Setup!A24 | B12: =Setup!B24 | C12: =Q11 | D12: =ROUND(C12*B12/12,2) | E12: =C12+D12 | F12: =Setup!$B$3*Setup!$C$9 | G12: =IF(Setup!C24>0,F12/Setup!C24,0) | H12: =H11+G12 | I12: =H12*Setup!E24 | J12: =H12*Setup!D24 | K12: =Setup!$B$3*Setup!$C$10 | L12: =IF(Setup!F24>0,K12/Setup!F24,0) | M12: =M11+L12 | N12: =M12*Setup!H24 | O12: =M12*Setup!G24 | P12: =I12+N12 | Q12: =E12+P12 | R12: =R11+F12+K12 | S12: =J12+O12 | T12: =ROUND(T11*(1+B12/12),2)+Setup!$B$3
A13: =Setup!A25 | B13: =Setup!B25 | C13: =Q12 | D13: =ROUND(C13*B13/12,2) | E13: =C13+D13 | F13: =Setup!$B$3*Setup!$C$9 | G13: =IF(Setup!C25>0,F13/Setup!C25,0) | H13: =H12+G13 | I13: =H13*Setup!E25 | J13: =H13*Setup!D25 | K13: =Setup!$B$3*Setup!$C$10 | L13: =IF(Setup!F25>0,K13/Setup!F25,0) | M13: =M12+L13 | N13: =M13*Setup!H25 | O13: =M13*Setup!G25 | P13: =I13+N13 | Q13: =E13+P13 | R13: =R12+F13+K13 | S13: =J13+O13 | T13: =ROUND(T12*(1+B13/12),2)+Setup!$B$3
A14: =Setup!A26 | B14: =Setup!B26 | C14: =Q13 | D14: =ROUND(C14*B14/12,2) | E14: =C14+D14 | F14: =Setup!$B$3*Setup!$C$9 | G14: =IF(Setup!C26>0,F14/Setup!C26,0) | H14: =H13+G14 | I14: =H14*Setup!E26 | J14: =H14*Setup!D26 | K14: =Setup!$B$3*Setup!$C$10 | L14: =IF(Setup!F26>0,K14/Setup!F26,0) | M14: =M13+L14 | N14: =M14*Setup!H26 | O14: =M14*Setup!G26 | P14: =I14+N14 | Q14: =E14+P14 | R14: =R13+F14+K14 | S14: =J14+O14 | T14: =ROUND(T13*(1+B14/12),2)+Setup!$B$3
... A38: =Setup!A50 | B38: =Setup!B50 | C38: =Q37 | D38: =ROUND(C38*B38/12,2) | E38: =C38+D38 | F38: =Setup!$B$3*Setup!$C$9 | G38: =IF(Setup!C50>0,F38/Setup!C50,0) | H38: =H37+G38 | I38: =H38*Setup!E50 | J38: =H38*Setup!D50 | K38: =Setup!$B$3*Setup!$C$10 | L38: =IF(Setup!F50>0,K38/Setup!F50,0) | M38: =M37+L38 | N38: =M38*Setup!H50 | O38: =M38*Setup!G50 | P38: =I38+N38 | Q38: =E38+P38 | R38: =R37+F38+K38 | S38: =J38+O38 | T38: =ROUND(T37*(1+B38/12),2)+Setup!$B$3

Sheet Year Summary
A1: Year | B1: Invested | C1: Cum Invested | D1: Dividends | E1: MM Interest | F1: End Stock Value | G1: End Div Bal
A2: 2023 | B2: =SUM('Monthly Sim'!F2:F12)+SUM('Monthly Sim'!K2:K12) | C2: ='Monthly Sim'!R12 | D2: =SUM('Monthly Sim'!P2:P12) | E2: =SUM('Monthly Sim'!D2:D12) | F2: ='Monthly Sim'!S12 | G2: ='Monthly Sim'!Q12
A3: 2024 | B3: =SUM('Monthly Sim'!F13:F24)+SUM('Monthly Sim'!K13:K24) | C3: ='Monthly Sim'!R24 | D3: =SUM('Monthly Sim'!P13:P24) | E3: =SUM('Monthly Sim'!D13:D24) | F3: ='Monthly Sim'!S24 | G3: ='Monthly Sim'!Q24
A4: 2025 | B4: =SUM('Monthly Sim'!F25:F36)+SUM('Monthly Sim'!K25:K36) | C4: ='Monthly Sim'!R36 | D4: =SUM('Monthly Sim'!P25:P36) | E4: =SUM('Monthly Sim'!D25:D36) | F4: ='Monthly Sim'!S36 | G4: ='Monthly Sim'!Q36
A5: 2026 | B5: =SUM('Monthly Sim'!F37:F38)+SUM('Monthly Sim'!K37:K38) | C5: ='Monthly Sim'!R38 | D5: =SUM('Monthly Sim'!P37:P38) | E5: =SUM('Monthly Sim'!D37:D38) | F5: ='Monthly Sim'!S38 | G5: ='Monthly Sim'!Q38

Sheet Tax Impact
A1: Year | B1: Dividends | C1: Tax on Dividends | D1: MM Interest | E1: Tax on Interest | F1: Total Taxes
A2: ='Year Summary'!A2 | B2: ='Year Summary'!D2 | C2: =B2*Setup!$B$5 | D2: ='Year Summary'!E2 | E2: =D2*Setup!$B$5 | F2: =C2+E2
A3: ='Year Summary'!A3 | B3: ='Year Summary'!D3 | C3: =B3*Setup!$B$5 | D3: ='Year Summary'!E3 | E3: =D3*Setup!$B$5 | F3: =C3+E3
A4: ='Year Summary'!A4 | B4: ='Year Summary'!D4 | C4: =B4*Setup!$B$5 | D4: ='Year Summary'!E4 | E4: =D4*Setup!$B$5 | F4: =C4+E4
A5: ='Year Summary'!A5 | B5: ='Year Summary'!D5 | C5: =B5*Setup!$B$5 | D5: ='Year Summary'!E5 | E5: =D5*Setup!$B$5 | F5: =C5+E5
A6: TOTAL | B6: =SUM(B2:B5) | C6: =SUM(C2:C5) | D6: =SUM(D2:D5) | E6: =SUM(E2:E5) | F6: =SUM(F2:F5)

Sheet Annual Returns
A1: Year | B1: Invested | C1: Dividends | D1: MM Interest | E1: Stock Value | F1: Portfolio Value | G1: After-Tax Value | H1: Pre-Tax Return | I1: After-Tax Return
A2: ='Year Summary'!A2 | B2: ='Year Summary'!B2 | C2: ='Year Summary'!D2 | D2: ='Year Summary'!E2 | E2: ='Year Summary'!F2 | F2: ='Year Summary'!F2+'Year Summary'!G2 | G2: =F2-'Tax Impact'!F2 | H2: =C9 | I2: =C10
B3: Beginning Stock Value | C3: 0
B4: Stock Gain | C4: =E2-C3-B2 | D4: End Stock Value - Beginning - Invested
B5: Avg Invested Capital | C5: =B2*0.542 | D5: Invested x 0.542 (DCA mid-year)
B6: Base Capital (Denominator) | C6: =C3+C5 | D6: Beginning Stock Value + Avg Invested
B7: Total Gain (Numerator) | C7: =C4+C2+D2 | D7: Stock Gain + Dividends + MM Interest
B8: After-Tax Gain | C8: =C4+(C2-'Tax Impact'!C2)+(D2-'Tax Impact'!E2) | D8: Stock Gain + (Divs-Tax) + (MMInt-Tax)
B9: Pre-Tax Return | C9: =IF(C6>0,C7/C6,0) | D9: Total Gain / Base Capital
B10: After-Tax Return | C10: =IF(C6>0,C8/C6,0) | D10: After-Tax Gain / Base Capital
A12: ='Year Summary'!A3 | B12: ='Year Summary'!B3 | C12: ='Year Summary'!D3 | D12: ='Year Summary'!E3 | E12: ='Year Summary'!F3 | F12: ='Year Summary'!F3+'Year Summary'!G3 | G12: =F12-'Tax Impact'!F3 | H12: =C19 | I12: =C20
B13: Beginning Stock Value | C13: ='Year Summary'!F2
B14: Stock Gain | C14: =E12-C13-B12 | D14: End Stock Value - Beginning - Invested
B15: Avg Invested Capital | C15: =B12*0.542 | D15: Invested x 0.542 (DCA mid-year)
B16: Base Capital (Denominator) | C16: =C13+C15 | D16: Beginning Stock Value + Avg Invested
B17: Total Gain (Numerator) | C17: =C14+C12+D12 | D17: Stock Gain + Dividends + MM Interest
B18: After-Tax Gain | C18: =C14+(C12-'Tax Impact'!C3)+(D12-'Tax Impact'!E3) | D18: Stock Gain + (Divs-Tax) + (MMInt-Tax)
B19: Pre-Tax Return | C19: =IF(C16>0,C17/C16,0) | D19: Total Gain / Base Capital
B20: After-Tax Return | C20: =IF(C16>0,C18/C16,0) | D20: After-Tax Gain / Base Capital
A22: ='Year Summary'!A4 | B22: ='Year Summary'!B4 | C22: ='Year Summary'!D4 | D22: ='Year Summary'!E4 | E22: ='Year Summary'!F4 | F22: ='Year Summary'!F4+'Year Summary'!G4 | G22: =F22-'Tax Impact'!F4 | H22: =C29 | I22: =C30
B23: Beginning Stock Value | C23: ='Year Summary'!F3
B24: Stock Gain | C24: =E22-C23-B22 | D24: End Stock Value - Beginning - Invested
B25: Avg Invested Capital | C25: =B22*0.542 | D25: Invested x 0.542 (DCA mid-year)
B26: Base Capital (Denominator) | C26: =C23+C25 | D26: Beginning Stock Value + Avg Invested
B27: Total Gain (Numerator) | C27: =C24+C22+D22 | D27: Stock Gain + Dividends + MM Interest
B28: After-Tax Gain | C28: =C24+(C22-'Tax Impact'!C4)+(D22-'Tax Impact'!E4) | D28: Stock Gain + (Divs-Tax) + (MMInt-Tax)
B29: Pre-Tax Return | C29: =IF(C26>0,C27/C26,0) | D29: Total Gain / Base Capital
B30: After-Tax Return | C30: =IF(C26>0,C28/C26,0) | D30: After-Tax Gain / Base Capital
A32: ='Year Summary'!A5 | B32: ='Year Summary'!B5 | C32: ='Year Summary'!D5 | D32: ='Year Summary'!E5 | E32: ='Year Summary'!F5 | F32: ='Year Summary'!F5+'Year Summary'!G5 | G32: =F32-'Tax Impact'!F5 | H32: =C39 | I32: =C40
B33: Beginning Stock Value | C33: ='Year Summary'!F4
B34: Stock Gain | C34: =E32-C33-B32 | D34: End Stock Value - Beginning - Invested
B35: Avg Invested Capital | C35: =B32*0.542 | D35: Invested x 0.542 (DCA mid-year)
B36: Base Capital (Denominator) | C36: =C33+C35 | D36: Beginning Stock Value + Avg Invested
B37: Total Gain (Numerator) | C37: =C34+C32+D32 | D37: Stock Gain + Dividends + MM Interest
B38: After-Tax Gain | C38: =C34+(C32-'Tax Impact'!C5)+(D32-'Tax Impact'!E5) | D38: Stock Gain + (Divs-Tax) + (MMInt-Tax)
B39: Pre-Tax Return | C39: =IF(C36>0,C37/C36,0) | D39: Total Gain / Base Capital
B40: After-Tax Return | C40: =IF(C36>0,C38/C36,0) | D40: After-Tax Gain / Base Capital
